autoliterature/__init__.py
autoliterature/arxiv.py
autoliterature/autoliter.py
autoliterature/crossref.py
autoliterature/downloads.py
autoliterature/medbiorxiv.py
autoliterature/pdfs.py
autoliterature/utils.py
autoliter-0.1.3.dist-info/METADATA
autoliter-0.1.3.dist-info/WHEEL
autoliter-0.1.3.dist-info/entry_points.txt
autoliter-0.1.3.dist-info/top_level.txt
autoliter-0.1.3.dist-info/RECORD
