Metadata-Version: 2.1
Name: autoliter
Version: 0.1.3
Summary: Helps you manage your literature notes
Home-page: https://github.com/WilmerWang/autoLiterature
Download-URL: https://github.com/WilmerWang/autoLiterature/archive/refs/tags/v0.1.3.tar.gz
Author: Wilmer Wang
Author-email: wangwei0206@foxmail.com
License: AGPLv3
Keywords: bibtex,arxiv,doi,science,scientific-journals
Classifier: License :: OSI Approved :: GNU Affero General Public License v3 or later (AGPLv3+)
Classifier: Intended Audience :: Science/Research
Classifier: Programming Language :: Python :: 3
Classifier: Topic :: Text Processing :: Markup
Requires-Dist: beautifulsoup4 (>=4.11.1)
Requires-Dist: feedparser (>=6.0.10)
Requires-Dist: urllib3 (>=1.26.11)
Requires-Dist: requests (>=2.28.1)
Requires-Dist: tqdm (>=4.64.0)
Requires-Dist: Unidecode (>=1.3.4)
